{
    "databases": {
        "postgres": {
            "level": "gold",
            "notes": ""
        },
        "mysql": {
            "level": "gold",
            "notes": ""
        },
        "sqlite": {
            "level": "gold",
            "notes": ""
        },
        "other": {
            "level": "bronze",
            "notes": "Supports CockroachDB, MariaDB, and TiDB"
        }
    },
    "features": {
        "ORM": {
            "level": "gold",
            "notes": ""
        },
        "Query Builder": {
            "level": "gold",
            "notes": ""
        },
        "Generic Mapper": {
            "level": "gold",
            "notes": ""
        }
    },
    "other": {
        "activity": {
            "level": "gold",
            "notes": "Under active development"
        },
        "documentation": {
            "level": "gold",
            "notes": "Dedicated documentation site, with examples"
        },
        "examples": {
            "level": "silver",
            "notes": "Has many examples, but generally only a single example per feature"
        },
        "migration": {
            "level": "gold",
            "notes": "Integrated with the Atlas migration system, which is a powerful migration tool"
        }
    }
}